finn_scraper/__init__.py
finn_scraper-0.0.0.dist-info/METADATA
finn_scraper-0.0.0.dist-info/WHEEL
finn_scraper-0.0.0.dist-info/top_level.txt
finn_scraper-0.0.0.dist-info/RECORD
