Metadata-Version: 2.1
Name: finn-scraper
Version: 0.0.0
Summary: A web scraper for finn.no
Author-email: Magnus Kristiansen <magnuskri99@gmail.com>
Classifier: Development Status :: 1 - Planning
